argtyped/__init__.py
argtyped/__version__.py
argtyped/arguments.py
argtyped/attrs_arguments.py
argtyped/custom_types.py
argtyped-0.4.0.dist-info/LICENSE
argtyped-0.4.0.dist-info/METADATA
argtyped-0.4.0.dist-info/WHEEL
argtyped-0.4.0.dist-info/top_level.txt
argtyped-0.4.0.dist-info/RECORD
